{
  "dataset_revision": "09698e0180d87dc247ca447d3a1248b931ac0cdb",
  "task_name": "XNLI",
  "mteb_version": "1.34.4",
  "scores": {
    "test": [
      {
        "similarity_accuracy": 0.570696,
        "similarity_accuracy_threshold": 0.733846,
        "similarity_f1": 0.666993,
        "similarity_f1_threshold": 0.151547,
        "similarity_precision": 0.500367,
        "similarity_recall": 1.0,
        "similarity_ap": 0.578186,
        "cosine_accuracy": 0.570696,
        "cosine_accuracy_threshold": 0.733846,
        "cosine_f1": 0.666993,
        "cosine_f1_threshold": 0.151547,
        "cosine_precision": 0.500367,
        "cosine_recall": 1.0,
        "cosine_ap": 0.578186,
        "manhattan_accuracy": 0.572161,
        "manhattan_accuracy_threshold": 7.959907,
        "manhattan_f1": 0.666994,
        "manhattan_f1_threshold": 13.185672,
        "manhattan_precision": 0.501105,
        "manhattan_recall": 0.997067,
        "manhattan_ap": 0.585356,
        "euclidean_accuracy": 0.570696,
        "euclidean_accuracy_threshold": 0.729595,
        "euclidean_f1": 0.666993,
        "euclidean_f1_threshold": 1.30261,
        "euclidean_precision": 0.500367,
        "euclidean_recall": 1.0,
        "euclidean_ap": 0.578186,
        "dot_accuracy": 0.570696,
        "dot_accuracy_threshold": 0.733846,
        "dot_f1": 0.666993,
        "dot_f1_threshold": 0.151547,
        "dot_precision": 0.500367,
        "dot_recall": 1.0,
        "dot_ap": 0.578186,
        "max_accuracy": 0.572161,
        "max_f1": 0.666994,
        "max_precision": 0.501105,
        "max_recall": 1.0,
        "max_ap": 0.585356,
        "main_score": 0.585356,
        "hf_subset": "ar",
        "languages": [
          "ara-Arab"
        ]
      },
      {
        "similarity_accuracy": 0.569231,
        "similarity_accuracy_threshold": 0.707108,
        "similarity_f1": 0.668347,
        "similarity_f1_threshold": 0.356056,
        "similarity_precision": 0.509217,
        "similarity_recall": 0.972141,
        "similarity_ap": 0.572934,
        "cosine_accuracy": 0.569231,
        "cosine_accuracy_threshold": 0.707108,
        "cosine_f1": 0.668347,
        "cosine_f1_threshold": 0.356056,
        "cosine_precision": 0.509217,
        "cosine_recall": 0.972141,
        "cosine_ap": 0.572934,
        "manhattan_accuracy": 0.567766,
        "manhattan_accuracy_threshold": 8.421547,
        "manhattan_f1": 0.668986,
        "manhattan_f1_threshold": 12.61322,
        "manhattan_precision": 0.506015,
        "manhattan_recall": 0.986804,
        "manhattan_ap": 0.57472,
        "euclidean_accuracy": 0.569231,
        "euclidean_accuracy_threshold": 0.765365,
        "euclidean_f1": 0.668347,
        "euclidean_f1_threshold": 1.134851,
        "euclidean_precision": 0.509217,
        "euclidean_recall": 0.972141,
        "euclidean_ap": 0.572934,
        "dot_accuracy": 0.569231,
        "dot_accuracy_threshold": 0.707108,
        "dot_f1": 0.668347,
        "dot_f1_threshold": 0.356056,
        "dot_precision": 0.509217,
        "dot_recall": 0.972141,
        "dot_ap": 0.572934,
        "max_accuracy": 0.569231,
        "max_f1": 0.668986,
        "max_precision": 0.509217,
        "max_recall": 0.986804,
        "max_ap": 0.57472,
        "main_score": 0.57472,
        "hf_subset": "bg",
        "languages": [
          "bul-Cyrl"
        ]
      },
      {
        "similarity_accuracy": 0.541392,
        "similarity_accuracy_threshold": 0.728524,
        "similarity_f1": 0.665689,
        "similarity_f1_threshold": 0.014026,
        "similarity_precision": 0.499267,
        "similarity_recall": 0.998534,
        "similarity_ap": 0.551601,
        "cosine_accuracy": 0.541392,
        "cosine_accuracy_threshold": 0.728524,
        "cosine_f1": 0.665689,
        "cosine_f1_threshold": 0.014026,
        "cosine_precision": 0.499267,
        "cosine_recall": 0.998534,
        "cosine_ap": 0.551601,
        "manhattan_accuracy": 0.54359,
        "manhattan_accuracy_threshold": 7.854809,
        "manhattan_f1": 0.665689,
        "manhattan_f1_threshold": 14.775072,
        "manhattan_precision": 0.499267,
        "manhattan_recall": 0.998534,
        "manhattan_ap": 0.564182,
        "euclidean_accuracy": 0.541392,
        "euclidean_accuracy_threshold": 0.736853,
        "euclidean_f1": 0.665689,
        "euclidean_f1_threshold": 1.404245,
        "euclidean_precision": 0.499267,
        "euclidean_recall": 0.998534,
        "euclidean_ap": 0.551601,
        "dot_accuracy": 0.541392,
        "dot_accuracy_threshold": 0.728524,
        "dot_f1": 0.665689,
        "dot_f1_threshold": 0.014026,
        "dot_precision": 0.499267,
        "dot_recall": 0.998534,
        "dot_ap": 0.551601,
        "max_accuracy": 0.54359,
        "max_f1": 0.665689,
        "max_precision": 0.499267,
        "max_recall": 0.998534,
        "max_ap": 0.564182,
        "main_score": 0.564182,
        "hf_subset": "de",
        "languages": [
          "deu-Latn"
        ]
      },
      {
        "similarity_accuracy": 0.556044,
        "similarity_accuracy_threshold": 0.751361,
        "similarity_f1": 0.667656,
        "similarity_f1_threshold": 0.343556,
        "similarity_precision": 0.503731,
        "similarity_recall": 0.989736,
        "similarity_ap": 0.569391,
        "cosine_accuracy": 0.556044,
        "cosine_accuracy_threshold": 0.751361,
        "cosine_f1": 0.667656,
        "cosine_f1_threshold": 0.343556,
        "cosine_precision": 0.503731,
        "cosine_recall": 0.989736,
        "cosine_ap": 0.569391,
        "manhattan_accuracy": 0.561905,
        "manhattan_accuracy_threshold": 7.748404,
        "manhattan_f1": 0.667974,
        "manhattan_f1_threshold": 12.925949,
        "manhattan_precision": 0.501842,
        "manhattan_recall": 0.998534,
        "manhattan_ap": 0.573948,
        "euclidean_accuracy": 0.556044,
        "euclidean_accuracy_threshold": 0.705179,
        "euclidean_f1": 0.667656,
        "euclidean_f1_threshold": 1.145812,
        "euclidean_precision": 0.503731,
        "euclidean_recall": 0.989736,
        "euclidean_ap": 0.569391,
        "dot_accuracy": 0.556044,
        "dot_accuracy_threshold": 0.751361,
        "dot_f1": 0.667656,
        "dot_f1_threshold": 0.343556,
        "dot_precision": 0.503731,
        "dot_recall": 0.989736,
        "dot_ap": 0.569391,
        "max_accuracy": 0.561905,
        "max_f1": 0.667974,
        "max_precision": 0.503731,
        "max_recall": 0.998534,
        "max_ap": 0.573948,
        "main_score": 0.573948,
        "hf_subset": "el",
        "languages": [
          "ell-Grek"
        ]
      },
      {
        "similarity_accuracy": 0.567766,
        "similarity_accuracy_threshold": 0.692048,
        "similarity_f1": 0.66798,
        "similarity_f1_threshold": 0.233602,
        "similarity_precision": 0.502967,
        "similarity_recall": 0.994135,
        "similarity_ap": 0.582139,
        "cosine_accuracy": 0.567766,
        "cosine_accuracy_threshold": 0.692048,
        "cosine_f1": 0.66798,
        "cosine_f1_threshold": 0.233602,
        "cosine_precision": 0.502967,
        "cosine_recall": 0.994135,
        "cosine_ap": 0.582139,
        "manhattan_accuracy": 0.572894,
        "manhattan_accuracy_threshold": 9.01192,
        "manhattan_f1": 0.673936,
        "manhattan_f1_threshold": 11.699354,
        "manhattan_precision": 0.521704,
        "manhattan_recall": 0.951613,
        "manhattan_ap": 0.591723,
        "euclidean_accuracy": 0.567766,
        "euclidean_accuracy_threshold": 0.784796,
        "euclidean_f1": 0.66798,
        "euclidean_f1_threshold": 1.23806,
        "euclidean_precision": 0.502967,
        "euclidean_recall": 0.994135,
        "euclidean_ap": 0.582139,
        "dot_accuracy": 0.567766,
        "dot_accuracy_threshold": 0.692048,
        "dot_f1": 0.66798,
        "dot_f1_threshold": 0.233602,
        "dot_precision": 0.502967,
        "dot_recall": 0.994135,
        "dot_ap": 0.582139,
        "max_accuracy": 0.572894,
        "max_f1": 0.673936,
        "max_precision": 0.521704,
        "max_recall": 0.994135,
        "max_ap": 0.591723,
        "main_score": 0.591723,
        "hf_subset": "en",
        "languages": [
          "eng-Latn"
        ]
      },
      {
        "similarity_accuracy": 0.572161,
        "similarity_accuracy_threshold": 0.686099,
        "similarity_f1": 0.667331,
        "similarity_f1_threshold": 0.268595,
        "similarity_precision": 0.505279,
        "similarity_recall": 0.982405,
        "similarity_ap": 0.584285,
        "cosine_accuracy": 0.572161,
        "cosine_accuracy_threshold": 0.686099,
        "cosine_f1": 0.667331,
        "cosine_f1_threshold": 0.268595,
        "cosine_precision": 0.505279,
        "cosine_recall": 0.982405,
        "cosine_ap": 0.584285,
        "manhattan_accuracy": 0.571429,
        "manhattan_accuracy_threshold": 9.505323,
        "manhattan_f1": 0.668636,
        "manhattan_f1_threshold": 13.701639,
        "manhattan_precision": 0.503336,
        "manhattan_recall": 0.995601,
        "manhattan_ap": 0.58871,
        "euclidean_accuracy": 0.572161,
        "euclidean_accuracy_threshold": 0.792339,
        "euclidean_f1": 0.667331,
        "euclidean_f1_threshold": 1.209464,
        "euclidean_precision": 0.505279,
        "euclidean_recall": 0.982405,
        "euclidean_ap": 0.584285,
        "dot_accuracy": 0.572161,
        "dot_accuracy_threshold": 0.686099,
        "dot_f1": 0.667331,
        "dot_f1_threshold": 0.268595,
        "dot_precision": 0.505279,
        "dot_recall": 0.982405,
        "dot_ap": 0.584285,
        "max_accuracy": 0.572161,
        "max_f1": 0.668636,
        "max_precision": 0.505279,
        "max_recall": 0.995601,
        "max_ap": 0.58871,
        "main_score": 0.58871,
        "hf_subset": "es",
        "languages": [
          "spa-Latn"
        ]
      },
      {
        "similarity_accuracy": 0.550183,
        "similarity_accuracy_threshold": 0.640429,
        "similarity_f1": 0.668352,
        "similarity_f1_threshold": 0.384485,
        "similarity_precision": 0.510031,
        "similarity_recall": 0.969208,
        "similarity_ap": 0.577616,
        "cosine_accuracy": 0.550183,
        "cosine_accuracy_threshold": 0.640429,
        "cosine_f1": 0.668352,
        "cosine_f1_threshold": 0.384485,
        "cosine_precision": 0.510031,
        "cosine_recall": 0.969208,
        "cosine_ap": 0.577616,
        "manhattan_accuracy": 0.558242,
        "manhattan_accuracy_threshold": 9.700138,
        "manhattan_f1": 0.671066,
        "manhattan_f1_threshold": 12.035689,
        "manhattan_precision": 0.513199,
        "manhattan_recall": 0.969208,
        "manhattan_ap": 0.580667,
        "euclidean_accuracy": 0.550183,
        "euclidean_accuracy_threshold": 0.848023,
        "euclidean_f1": 0.668352,
        "euclidean_f1_threshold": 1.109518,
        "euclidean_precision": 0.510031,
        "euclidean_recall": 0.969208,
        "euclidean_ap": 0.577616,
        "dot_accuracy": 0.550183,
        "dot_accuracy_threshold": 0.640429,
        "dot_f1": 0.668352,
        "dot_f1_threshold": 0.384485,
        "dot_precision": 0.510031,
        "dot_recall": 0.969208,
        "dot_ap": 0.577616,
        "max_accuracy": 0.558242,
        "max_f1": 0.671066,
        "max_precision": 0.513199,
        "max_recall": 0.969208,
        "max_ap": 0.580667,
        "main_score": 0.580667,
        "hf_subset": "fr",
        "languages": [
          "fra-Latn"
        ]
      },
      {
        "similarity_accuracy": 0.545055,
        "similarity_accuracy_threshold": 0.785044,
        "similarity_f1": 0.66732,
        "similarity_f1_threshold": 0.215039,
        "similarity_precision": 0.501104,
        "similarity_recall": 0.998534,
        "similarity_ap": 0.567513,
        "cosine_accuracy": 0.545055,
        "cosine_accuracy_threshold": 0.785044,
        "cosine_f1": 0.66732,
        "cosine_f1_threshold": 0.215039,
        "cosine_precision": 0.501104,
        "cosine_recall": 0.998534,
        "cosine_ap": 0.567513,
        "manhattan_accuracy": 0.547253,
        "manhattan_accuracy_threshold": 7.527185,
        "manhattan_f1": 0.666995,
        "manhattan_f1_threshold": 12.675726,
        "manhattan_precision": 0.502226,
        "manhattan_recall": 0.992669,
        "manhattan_ap": 0.572128,
        "euclidean_accuracy": 0.545055,
        "euclidean_accuracy_threshold": 0.655676,
        "euclidean_f1": 0.66732,
        "euclidean_f1_threshold": 1.252953,
        "euclidean_precision": 0.501104,
        "euclidean_recall": 0.998534,
        "euclidean_ap": 0.567513,
        "dot_accuracy": 0.545055,
        "dot_accuracy_threshold": 0.785044,
        "dot_f1": 0.66732,
        "dot_f1_threshold": 0.215039,
        "dot_precision": 0.501104,
        "dot_recall": 0.998534,
        "dot_ap": 0.567513,
        "max_accuracy": 0.547253,
        "max_f1": 0.66732,
        "max_precision": 0.502226,
        "max_recall": 0.998534,
        "max_ap": 0.572128,
        "main_score": 0.572128,
        "hf_subset": "hi",
        "languages": [
          "hin-Deva"
        ]
      },
      {
        "similarity_accuracy": 0.547253,
        "similarity_accuracy_threshold": 0.738953,
        "similarity_f1": 0.667327,
        "similarity_f1_threshold": 0.205257,
        "similarity_precision": 0.503737,
        "similarity_recall": 0.98827,
        "similarity_ap": 0.573372,
        "cosine_accuracy": 0.547253,
        "cosine_accuracy_threshold": 0.738953,
        "cosine_f1": 0.667327,
        "cosine_f1_threshold": 0.205257,
        "cosine_precision": 0.503737,
        "cosine_recall": 0.98827,
        "cosine_ap": 0.573372,
        "manhattan_accuracy": 0.550183,
        "manhattan_accuracy_threshold": 8.329835,
        "manhattan_f1": 0.668693,
        "manhattan_f1_threshold": 12.631059,
        "manhattan_precision": 0.510836,
        "manhattan_recall": 0.967742,
        "manhattan_ap": 0.578914,
        "euclidean_accuracy": 0.547253,
        "euclidean_accuracy_threshold": 0.722561,
        "euclidean_f1": 0.667327,
        "euclidean_f1_threshold": 1.260743,
        "euclidean_precision": 0.503737,
        "euclidean_recall": 0.98827,
        "euclidean_ap": 0.573371,
        "dot_accuracy": 0.547253,
        "dot_accuracy_threshold": 0.738953,
        "dot_f1": 0.667327,
        "dot_f1_threshold": 0.205257,
        "dot_precision": 0.503737,
        "dot_recall": 0.98827,
        "dot_ap": 0.573372,
        "max_accuracy": 0.550183,
        "max_f1": 0.668693,
        "max_precision": 0.510836,
        "max_recall": 0.98827,
        "max_ap": 0.578914,
        "main_score": 0.578914,
        "hf_subset": "ru",
        "languages": [
          "rus-Cyrl"
        ]
      },
      {
        "similarity_accuracy": 0.556777,
        "similarity_accuracy_threshold": 0.510314,
        "similarity_f1": 0.665689,
        "similarity_f1_threshold": -0.069948,
        "similarity_precision": 0.499267,
        "similarity_recall": 0.998534,
        "similarity_ap": 0.569334,
        "cosine_accuracy": 0.556777,
        "cosine_accuracy_threshold": 0.510314,
        "cosine_f1": 0.665689,
        "cosine_f1_threshold": -0.069948,
        "cosine_precision": 0.499267,
        "cosine_recall": 0.998534,
        "cosine_ap": 0.569334,
        "manhattan_accuracy": 0.564103,
        "manhattan_accuracy_threshold": 10.82599,
        "manhattan_f1": 0.669367,
        "manhattan_f1_threshold": 13.097588,
        "manhattan_precision": 0.511214,
        "manhattan_recall": 0.969208,
        "manhattan_ap": 0.572489,
        "euclidean_accuracy": 0.556777,
        "euclidean_accuracy_threshold": 0.989632,
        "euclidean_f1": 0.665689,
        "euclidean_f1_threshold": 1.46246,
        "euclidean_precision": 0.499267,
        "euclidean_recall": 0.998534,
        "euclidean_ap": 0.569334,
        "dot_accuracy": 0.556777,
        "dot_accuracy_threshold": 0.510314,
        "dot_f1": 0.665689,
        "dot_f1_threshold": -0.069948,
        "dot_precision": 0.499267,
        "dot_recall": 0.998534,
        "dot_ap": 0.569334,
        "max_accuracy": 0.564103,
        "max_f1": 0.669367,
        "max_precision": 0.511214,
        "max_recall": 0.998534,
        "max_ap": 0.572489,
        "main_score": 0.572489,
        "hf_subset": "sw",
        "languages": [
          "swa-Latn"
        ]
      },
      {
        "similarity_accuracy": 0.539927,
        "similarity_accuracy_threshold": 0.904128,
        "similarity_f1": 0.667321,
        "similarity_f1_threshold": 0.308134,
        "similarity_precision": 0.501475,
        "similarity_recall": 0.997067,
        "similarity_ap": 0.543932,
        "cosine_accuracy": 0.539927,
        "cosine_accuracy_threshold": 0.904128,
        "cosine_f1": 0.667321,
        "cosine_f1_threshold": 0.308134,
        "cosine_precision": 0.501475,
        "cosine_recall": 0.997067,
        "cosine_ap": 0.543932,
        "manhattan_accuracy": 0.539194,
        "manhattan_accuracy_threshold": 6.855358,
        "manhattan_f1": 0.666993,
        "manhattan_f1_threshold": 13.330939,
        "manhattan_precision": 0.500735,
        "manhattan_recall": 0.998534,
        "manhattan_ap": 0.543343,
        "euclidean_accuracy": 0.539927,
        "euclidean_accuracy_threshold": 0.437887,
        "euclidean_f1": 0.667321,
        "euclidean_f1_threshold": 1.176321,
        "euclidean_precision": 0.501475,
        "euclidean_recall": 0.997067,
        "euclidean_ap": 0.543943,
        "dot_accuracy": 0.540659,
        "dot_accuracy_threshold": 0.904128,
        "dot_f1": 0.666667,
        "dot_f1_threshold": 0.0,
        "dot_precision": 0.502229,
        "dot_recall": 0.991202,
        "dot_ap": 0.54764,
        "max_accuracy": 0.540659,
        "max_f1": 0.667321,
        "max_precision": 0.502229,
        "max_recall": 0.998534,
        "max_ap": 0.54764,
        "main_score": 0.54764,
        "hf_subset": "th",
        "languages": [
          "tha-Thai"
        ]
      },
      {
        "similarity_accuracy": 0.567766,
        "similarity_accuracy_threshold": 0.605355,
        "similarity_f1": 0.66765,
        "similarity_f1_threshold": 0.104004,
        "similarity_precision": 0.502219,
        "similarity_recall": 0.995601,
        "similarity_ap": 0.599162,
        "cosine_accuracy": 0.567766,
        "cosine_accuracy_threshold": 0.605355,
        "cosine_f1": 0.66765,
        "cosine_f1_threshold": 0.104004,
        "cosine_precision": 0.502219,
        "cosine_recall": 0.995601,
        "cosine_ap": 0.599162,
        "manhattan_accuracy": 0.568498,
        "manhattan_accuracy_threshold": 9.430761,
        "manhattan_f1": 0.670641,
        "manhattan_f1_threshold": 13.58934,
        "manhattan_precision": 0.507137,
        "manhattan_recall": 0.989736,
        "manhattan_ap": 0.606912,
        "euclidean_accuracy": 0.567766,
        "euclidean_accuracy_threshold": 0.88842,
        "euclidean_f1": 0.66765,
        "euclidean_f1_threshold": 1.33864,
        "euclidean_precision": 0.502219,
        "euclidean_recall": 0.995601,
        "euclidean_ap": 0.599162,
        "dot_accuracy": 0.567766,
        "dot_accuracy_threshold": 0.605355,
        "dot_f1": 0.66765,
        "dot_f1_threshold": 0.104004,
        "dot_precision": 0.502219,
        "dot_recall": 0.995601,
        "dot_ap": 0.599162,
        "max_accuracy": 0.568498,
        "max_f1": 0.670641,
        "max_precision": 0.507137,
        "max_recall": 0.995601,
        "max_ap": 0.606912,
        "main_score": 0.606912,
        "hf_subset": "tr",
        "languages": [
          "tur-Latn"
        ]
      },
      {
        "similarity_accuracy": 0.569963,
        "similarity_accuracy_threshold": 0.701085,
        "similarity_f1": 0.667319,
        "similarity_f1_threshold": 0.143597,
        "similarity_precision": 0.500734,
        "similarity_recall": 1.0,
        "similarity_ap": 0.574441,
        "cosine_accuracy": 0.569963,
        "cosine_accuracy_threshold": 0.701085,
        "cosine_f1": 0.667319,
        "cosine_f1_threshold": 0.143597,
        "cosine_precision": 0.500734,
        "cosine_recall": 1.0,
        "cosine_ap": 0.574441,
        "manhattan_accuracy": 0.572161,
        "manhattan_accuracy_threshold": 8.431901,
        "manhattan_f1": 0.667376,
        "manhattan_f1_threshold": 10.427894,
        "manhattan_precision": 0.52381,
        "manhattan_recall": 0.919355,
        "manhattan_ap": 0.578677,
        "euclidean_accuracy": 0.569963,
        "euclidean_accuracy_threshold": 0.773195,
        "euclidean_f1": 0.667319,
        "euclidean_f1_threshold": 1.308647,
        "euclidean_precision": 0.500734,
        "euclidean_recall": 1.0,
        "euclidean_ap": 0.574441,
        "dot_accuracy": 0.569963,
        "dot_accuracy_threshold": 0.701085,
        "dot_f1": 0.667319,
        "dot_f1_threshold": 0.143597,
        "dot_precision": 0.500734,
        "dot_recall": 1.0,
        "dot_ap": 0.574441,
        "max_accuracy": 0.572161,
        "max_f1": 0.667376,
        "max_precision": 0.52381,
        "max_recall": 1.0,
        "max_ap": 0.578677,
        "main_score": 0.578677,
        "hf_subset": "vi",
        "languages": [
          "vie-Latn"
        ]
      },
      {
        "similarity_accuracy": 0.56044,
        "similarity_accuracy_threshold": 0.88314,
        "similarity_f1": 0.666341,
        "similarity_f1_threshold": 0.535023,
        "similarity_precision": 0.5,
        "similarity_recall": 0.998534,
        "similarity_ap": 0.589555,
        "cosine_accuracy": 0.56044,
        "cosine_accuracy_threshold": 0.88314,
        "cosine_f1": 0.666341,
        "cosine_f1_threshold": 0.535023,
        "cosine_precision": 0.5,
        "cosine_recall": 0.998534,
        "cosine_ap": 0.589555,
        "manhattan_accuracy": 0.565568,
        "manhattan_accuracy_threshold": 5.694517,
        "manhattan_f1": 0.666999,
        "manhattan_f1_threshold": 9.108272,
        "manhattan_precision": 0.505287,
        "manhattan_recall": 0.980938,
        "manhattan_ap": 0.587873,
        "euclidean_accuracy": 0.56044,
        "euclidean_accuracy_threshold": 0.483445,
        "euclidean_f1": 0.666341,
        "euclidean_f1_threshold": 0.96434,
        "euclidean_precision": 0.5,
        "euclidean_recall": 0.998534,
        "euclidean_ap": 0.589555,
        "dot_accuracy": 0.56044,
        "dot_accuracy_threshold": 0.88314,
        "dot_f1": 0.666341,
        "dot_f1_threshold": 0.535023,
        "dot_precision": 0.5,
        "dot_recall": 0.998534,
        "dot_ap": 0.589555,
        "max_accuracy": 0.565568,
        "max_f1": 0.666999,
        "max_precision": 0.505287,
        "max_recall": 0.998534,
        "max_ap": 0.589555,
        "main_score": 0.589555,
        "hf_subset": "zh",
        "languages": [
          "zho-Hans"
        ]
      }
    ],
    "validation": [
      {
        "similarity_accuracy": 0.589011,
        "similarity_accuracy_threshold": 0.653275,
        "similarity_f1": 0.666994,
        "similarity_f1_threshold": 0.273416,
        "similarity_precision": 0.501477,
        "similarity_recall": 0.995601,
        "similarity_ap": 0.61525,
        "cosine_accuracy": 0.589011,
        "cosine_accuracy_threshold": 0.653275,
        "cosine_f1": 0.666994,
        "cosine_f1_threshold": 0.273416,
        "cosine_precision": 0.501477,
        "cosine_recall": 0.995601,
        "cosine_ap": 0.61525,
        "manhattan_accuracy": 0.586081,
        "manhattan_accuracy_threshold": 9.181909,
        "manhattan_f1": 0.667005,
        "manhattan_f1_threshold": 11.550471,
        "manhattan_precision": 0.510093,
        "manhattan_recall": 0.963343,
        "manhattan_ap": 0.615928,
        "euclidean_accuracy": 0.589011,
        "euclidean_accuracy_threshold": 0.832736,
        "euclidean_f1": 0.666994,
        "euclidean_f1_threshold": 1.205474,
        "euclidean_precision": 0.501477,
        "euclidean_recall": 0.995601,
        "euclidean_ap": 0.61525,
        "dot_accuracy": 0.589011,
        "dot_accuracy_threshold": 0.653275,
        "dot_f1": 0.666994,
        "dot_f1_threshold": 0.273416,
        "dot_precision": 0.501477,
        "dot_recall": 0.995601,
        "dot_ap": 0.61525,
        "max_accuracy": 0.589011,
        "max_f1": 0.667005,
        "max_precision": 0.510093,
        "max_recall": 0.995601,
        "max_ap": 0.615928,
        "main_score": 0.615928,
        "hf_subset": "ar",
        "languages": [
          "ara-Arab"
        ]
      },
      {
        "similarity_accuracy": 0.586813,
        "similarity_accuracy_threshold": 0.702053,
        "similarity_f1": 0.666993,
        "similarity_f1_threshold": 0.017166,
        "similarity_precision": 0.500367,
        "similarity_recall": 1.0,
        "similarity_ap": 0.596097,
        "cosine_accuracy": 0.586813,
        "cosine_accuracy_threshold": 0.702053,
        "cosine_f1": 0.666993,
        "cosine_f1_threshold": 0.017166,
        "cosine_precision": 0.500367,
        "cosine_recall": 1.0,
        "cosine_ap": 0.596097,
        "manhattan_accuracy": 0.597802,
        "manhattan_accuracy_threshold": 8.920016,
        "manhattan_f1": 0.668027,
        "manhattan_f1_threshold": 11.87861,
        "manhattan_precision": 0.512119,
        "manhattan_recall": 0.960411,
        "manhattan_ap": 0.603407,
        "euclidean_accuracy": 0.586813,
        "euclidean_accuracy_threshold": 0.771942,
        "euclidean_f1": 0.666993,
        "euclidean_f1_threshold": 1.401726,
        "euclidean_precision": 0.500367,
        "euclidean_recall": 1.0,
        "euclidean_ap": 0.596097,
        "dot_accuracy": 0.586813,
        "dot_accuracy_threshold": 0.702053,
        "dot_f1": 0.666993,
        "dot_f1_threshold": 0.017166,
        "dot_precision": 0.500367,
        "dot_recall": 1.0,
        "dot_ap": 0.596097,
        "max_accuracy": 0.597802,
        "max_f1": 0.668027,
        "max_precision": 0.512119,
        "max_recall": 1.0,
        "max_ap": 0.603407,
        "main_score": 0.603407,
        "hf_subset": "bg",
        "languages": [
          "bul-Cyrl"
        ]
      },
      {
        "similarity_accuracy": 0.571429,
        "similarity_accuracy_threshold": 0.67994,
        "similarity_f1": 0.666993,
        "similarity_f1_threshold": -0.034319,
        "similarity_precision": 0.500367,
        "similarity_recall": 1.0,
        "similarity_ap": 0.598145,
        "cosine_accuracy": 0.571429,
        "cosine_accuracy_threshold": 0.67994,
        "cosine_f1": 0.666993,
        "cosine_f1_threshold": -0.034319,
        "cosine_precision": 0.500367,
        "cosine_recall": 1.0,
        "cosine_ap": 0.598145,
        "manhattan_accuracy": 0.574359,
        "manhattan_accuracy_threshold": 9.54519,
        "manhattan_f1": 0.667321,
        "manhattan_f1_threshold": 14.102422,
        "manhattan_precision": 0.501475,
        "manhattan_recall": 0.997067,
        "manhattan_ap": 0.603677,
        "euclidean_accuracy": 0.571429,
        "euclidean_accuracy_threshold": 0.800074,
        "euclidean_f1": 0.666993,
        "euclidean_f1_threshold": 1.438274,
        "euclidean_precision": 0.500367,
        "euclidean_recall": 1.0,
        "euclidean_ap": 0.598145,
        "dot_accuracy": 0.571429,
        "dot_accuracy_threshold": 0.67994,
        "dot_f1": 0.666993,
        "dot_f1_threshold": -0.034319,
        "dot_precision": 0.500367,
        "dot_recall": 1.0,
        "dot_ap": 0.598145,
        "max_accuracy": 0.574359,
        "max_f1": 0.667321,
        "max_precision": 0.501475,
        "max_recall": 1.0,
        "max_ap": 0.603677,
        "main_score": 0.603677,
        "hf_subset": "de",
        "languages": [
          "deu-Latn"
        ]
      },
      {
        "similarity_accuracy": 0.585348,
        "similarity_accuracy_threshold": 0.764513,
        "similarity_f1": 0.666993,
        "similarity_f1_threshold": 0.118661,
        "similarity_precision": 0.500367,
        "similarity_recall": 1.0,
        "similarity_ap": 0.604196,
        "cosine_accuracy": 0.585348,
        "cosine_accuracy_threshold": 0.764513,
        "cosine_f1": 0.666993,
        "cosine_f1_threshold": 0.118661,
        "cosine_precision": 0.500367,
        "cosine_recall": 1.0,
        "cosine_ap": 0.604196,
        "manhattan_accuracy": 0.587546,
        "manhattan_accuracy_threshold": 7.640681,
        "manhattan_f1": 0.666993,
        "manhattan_f1_threshold": 14.139706,
        "manhattan_precision": 0.500367,
        "manhattan_recall": 1.0,
        "manhattan_ap": 0.607853,
        "euclidean_accuracy": 0.585348,
        "euclidean_accuracy_threshold": 0.686276,
        "euclidean_f1": 0.666993,
        "euclidean_f1_threshold": 1.327346,
        "euclidean_precision": 0.500367,
        "euclidean_recall": 1.0,
        "euclidean_ap": 0.604196,
        "dot_accuracy": 0.585348,
        "dot_accuracy_threshold": 0.764513,
        "dot_f1": 0.666993,
        "dot_f1_threshold": 0.118661,
        "dot_precision": 0.500367,
        "dot_recall": 1.0,
        "dot_ap": 0.604196,
        "max_accuracy": 0.587546,
        "max_f1": 0.666993,
        "max_precision": 0.500367,
        "max_recall": 1.0,
        "max_ap": 0.607853,
        "main_score": 0.607853,
        "hf_subset": "el",
        "languages": [
          "ell-Grek"
        ]
      },
      {
        "similarity_accuracy": 0.616117,
        "similarity_accuracy_threshold": 0.715927,
        "similarity_f1": 0.672302,
        "similarity_f1_threshold": 0.278869,
        "similarity_precision": 0.508653,
        "similarity_recall": 0.991202,
        "similarity_ap": 0.636137,
        "cosine_accuracy": 0.616117,
        "cosine_accuracy_threshold": 0.715927,
        "cosine_f1": 0.672302,
        "cosine_f1_threshold": 0.278869,
        "cosine_precision": 0.508653,
        "cosine_recall": 0.991202,
        "cosine_ap": 0.636137,
        "manhattan_accuracy": 0.621245,
        "manhattan_accuracy_threshold": 8.325992,
        "manhattan_f1": 0.671612,
        "manhattan_f1_threshold": 12.912249,
        "manhattan_precision": 0.506716,
        "manhattan_recall": 0.995601,
        "manhattan_ap": 0.641011,
        "euclidean_accuracy": 0.616117,
        "euclidean_accuracy_threshold": 0.753755,
        "euclidean_f1": 0.672302,
        "euclidean_f1_threshold": 1.20094,
        "euclidean_precision": 0.508653,
        "euclidean_recall": 0.991202,
        "euclidean_ap": 0.636137,
        "dot_accuracy": 0.616117,
        "dot_accuracy_threshold": 0.715927,
        "dot_f1": 0.672302,
        "dot_f1_threshold": 0.278869,
        "dot_precision": 0.508653,
        "dot_recall": 0.991202,
        "dot_ap": 0.636137,
        "max_accuracy": 0.621245,
        "max_f1": 0.672302,
        "max_precision": 0.508653,
        "max_recall": 0.995601,
        "max_ap": 0.641011,
        "main_score": 0.641011,
        "hf_subset": "en",
        "languages": [
          "eng-Latn"
        ]
      },
      {
        "similarity_accuracy": 0.605861,
        "similarity_accuracy_threshold": 0.637266,
        "similarity_f1": 0.667974,
        "similarity_f1_threshold": 0.113087,
        "similarity_precision": 0.501842,
        "similarity_recall": 0.998534,
        "similarity_ap": 0.632355,
        "cosine_accuracy": 0.605861,
        "cosine_accuracy_threshold": 0.637266,
        "cosine_f1": 0.667974,
        "cosine_f1_threshold": 0.113087,
        "cosine_precision": 0.501842,
        "cosine_recall": 0.998534,
        "cosine_ap": 0.632355,
        "manhattan_accuracy": 0.606593,
        "manhattan_accuracy_threshold": 8.935519,
        "manhattan_f1": 0.670757,
        "manhattan_f1_threshold": 12.739547,
        "manhattan_precision": 0.514914,
        "manhattan_recall": 0.961877,
        "manhattan_ap": 0.633571,
        "euclidean_accuracy": 0.605861,
        "euclidean_accuracy_threshold": 0.851744,
        "euclidean_f1": 0.667974,
        "euclidean_f1_threshold": 1.33185,
        "euclidean_precision": 0.501842,
        "euclidean_recall": 0.998534,
        "euclidean_ap": 0.632355,
        "dot_accuracy": 0.605861,
        "dot_accuracy_threshold": 0.637266,
        "dot_f1": 0.667974,
        "dot_f1_threshold": 0.113087,
        "dot_precision": 0.501842,
        "dot_recall": 0.998534,
        "dot_ap": 0.632355,
        "max_accuracy": 0.606593,
        "max_f1": 0.670757,
        "max_precision": 0.514914,
        "max_recall": 0.998534,
        "max_ap": 0.633571,
        "main_score": 0.633571,
        "hf_subset": "es",
        "languages": [
          "spa-Latn"
        ]
      },
      {
        "similarity_accuracy": 0.599267,
        "similarity_accuracy_threshold": 0.71492,
        "similarity_f1": 0.66831,
        "similarity_f1_threshold": 0.240449,
        "similarity_precision": 0.503341,
        "similarity_recall": 0.994135,
        "similarity_ap": 0.610166,
        "cosine_accuracy": 0.599267,
        "cosine_accuracy_threshold": 0.71492,
        "cosine_f1": 0.66831,
        "cosine_f1_threshold": 0.240449,
        "cosine_precision": 0.503341,
        "cosine_recall": 0.994135,
        "cosine_ap": 0.610166,
        "manhattan_accuracy": 0.611722,
        "manhattan_accuracy_threshold": 8.78035,
        "manhattan_f1": 0.670641,
        "manhattan_f1_threshold": 12.680048,
        "manhattan_precision": 0.507137,
        "manhattan_recall": 0.989736,
        "manhattan_ap": 0.620876,
        "euclidean_accuracy": 0.599267,
        "euclidean_accuracy_threshold": 0.75509,
        "euclidean_f1": 0.66831,
        "euclidean_f1_threshold": 1.232498,
        "euclidean_precision": 0.503341,
        "euclidean_recall": 0.994135,
        "euclidean_ap": 0.610166,
        "dot_accuracy": 0.599267,
        "dot_accuracy_threshold": 0.71492,
        "dot_f1": 0.66831,
        "dot_f1_threshold": 0.240449,
        "dot_precision": 0.503341,
        "dot_recall": 0.994135,
        "dot_ap": 0.610166,
        "max_accuracy": 0.611722,
        "max_f1": 0.670641,
        "max_precision": 0.507137,
        "max_recall": 0.994135,
        "max_ap": 0.620876,
        "main_score": 0.620876,
        "hf_subset": "fr",
        "languages": [
          "fra-Latn"
        ]
      },
      {
        "similarity_accuracy": 0.556777,
        "similarity_accuracy_threshold": 0.736906,
        "similarity_f1": 0.666993,
        "similarity_f1_threshold": 0.125371,
        "similarity_precision": 0.500735,
        "similarity_recall": 0.998534,
        "similarity_ap": 0.566571,
        "cosine_accuracy": 0.556777,
        "cosine_accuracy_threshold": 0.736906,
        "cosine_f1": 0.666993,
        "cosine_f1_threshold": 0.125371,
        "cosine_precision": 0.500735,
        "cosine_recall": 0.998534,
        "cosine_ap": 0.566571,
        "manhattan_accuracy": 0.561172,
        "manhattan_accuracy_threshold": 7.680815,
        "manhattan_f1": 0.667973,
        "manhattan_f1_threshold": 13.694581,
        "manhattan_precision": 0.501471,
        "manhattan_recall": 1.0,
        "manhattan_ap": 0.567804,
        "euclidean_accuracy": 0.556777,
        "euclidean_accuracy_threshold": 0.725388,
        "euclidean_f1": 0.666993,
        "euclidean_f1_threshold": 1.322587,
        "euclidean_precision": 0.500735,
        "euclidean_recall": 0.998534,
        "euclidean_ap": 0.566571,
        "dot_accuracy": 0.556777,
        "dot_accuracy_threshold": 0.736906,
        "dot_f1": 0.666993,
        "dot_f1_threshold": 0.125371,
        "dot_precision": 0.500735,
        "dot_recall": 0.998534,
        "dot_ap": 0.566571,
        "max_accuracy": 0.561172,
        "max_f1": 0.667973,
        "max_precision": 0.501471,
        "max_recall": 1.0,
        "max_ap": 0.567804,
        "main_score": 0.567804,
        "hf_subset": "hi",
        "languages": [
          "hin-Deva"
        ]
      },
      {
        "similarity_accuracy": 0.550916,
        "similarity_accuracy_threshold": 0.700327,
        "similarity_f1": 0.667651,
        "similarity_f1_threshold": 0.192496,
        "similarity_precision": 0.502595,
        "similarity_recall": 0.994135,
        "similarity_ap": 0.579418,
        "cosine_accuracy": 0.550916,
        "cosine_accuracy_threshold": 0.700327,
        "cosine_f1": 0.667651,
        "cosine_f1_threshold": 0.192496,
        "cosine_precision": 0.502595,
        "cosine_recall": 0.994135,
        "cosine_ap": 0.579418,
        "manhattan_accuracy": 0.558242,
        "manhattan_accuracy_threshold": 9.538831,
        "manhattan_f1": 0.667323,
        "manhattan_f1_threshold": 13.65802,
        "manhattan_precision": 0.502222,
        "manhattan_recall": 0.994135,
        "manhattan_ap": 0.584484,
        "euclidean_accuracy": 0.550916,
        "euclidean_accuracy_threshold": 0.774175,
        "euclidean_f1": 0.667651,
        "euclidean_f1_threshold": 1.270829,
        "euclidean_precision": 0.502595,
        "euclidean_recall": 0.994135,
        "euclidean_ap": 0.579418,
        "dot_accuracy": 0.550916,
        "dot_accuracy_threshold": 0.700327,
        "dot_f1": 0.667651,
        "dot_f1_threshold": 0.192496,
        "dot_precision": 0.502595,
        "dot_recall": 0.994135,
        "dot_ap": 0.579418,
        "max_accuracy": 0.558242,
        "max_f1": 0.667651,
        "max_precision": 0.502595,
        "max_recall": 0.994135,
        "max_ap": 0.584484,
        "main_score": 0.584484,
        "hf_subset": "ru",
        "languages": [
          "rus-Cyrl"
        ]
      },
      {
        "similarity_accuracy": 0.591209,
        "similarity_accuracy_threshold": 0.563184,
        "similarity_f1": 0.666341,
        "similarity_f1_threshold": -0.006711,
        "similarity_precision": 0.5,
        "similarity_recall": 0.998534,
        "similarity_ap": 0.600111,
        "cosine_accuracy": 0.591209,
        "cosine_accuracy_threshold": 0.563184,
        "cosine_f1": 0.666341,
        "cosine_f1_threshold": -0.006711,
        "cosine_precision": 0.5,
        "cosine_recall": 0.998534,
        "cosine_ap": 0.600111,
        "manhattan_accuracy": 0.598535,
        "manhattan_accuracy_threshold": 10.724464,
        "manhattan_f1": 0.667976,
        "manhattan_f1_threshold": 14.587246,
        "manhattan_precision": 0.502216,
        "manhattan_recall": 0.997067,
        "manhattan_ap": 0.609657,
        "euclidean_accuracy": 0.591209,
        "euclidean_accuracy_threshold": 0.934683,
        "euclidean_f1": 0.666341,
        "euclidean_f1_threshold": 1.41895,
        "euclidean_precision": 0.5,
        "euclidean_recall": 0.998534,
        "euclidean_ap": 0.600111,
        "dot_accuracy": 0.591209,
        "dot_accuracy_threshold": 0.563184,
        "dot_f1": 0.666341,
        "dot_f1_threshold": -0.006711,
        "dot_precision": 0.5,
        "dot_recall": 0.998534,
        "dot_ap": 0.600111,
        "max_accuracy": 0.598535,
        "max_f1": 0.667976,
        "max_precision": 0.502216,
        "max_recall": 0.998534,
        "max_ap": 0.609657,
        "main_score": 0.609657,
        "hf_subset": "sw",
        "languages": [
          "swa-Latn"
        ]
      },
      {
        "similarity_accuracy": 0.541392,
        "similarity_accuracy_threshold": 0.870653,
        "similarity_f1": 0.667646,
        "similarity_f1_threshold": 0.027177,
        "similarity_precision": 0.501102,
        "similarity_recall": 1.0,
        "similarity_ap": 0.564258,
        "cosine_accuracy": 0.541392,
        "cosine_accuracy_threshold": 0.870653,
        "cosine_f1": 0.667646,
        "cosine_f1_threshold": 0.027177,
        "cosine_precision": 0.501102,
        "cosine_recall": 1.0,
        "cosine_ap": 0.564258,
        "manhattan_accuracy": 0.541392,
        "manhattan_accuracy_threshold": 5.675186,
        "manhattan_f1": 0.66733,
        "manhattan_f1_threshold": 10.798136,
        "manhattan_precision": 0.504891,
        "manhattan_recall": 0.983871,
        "manhattan_ap": 0.559557,
        "euclidean_accuracy": 0.541392,
        "euclidean_accuracy_threshold": 0.508619,
        "euclidean_f1": 0.667646,
        "euclidean_f1_threshold": 1.394864,
        "euclidean_precision": 0.501102,
        "euclidean_recall": 1.0,
        "euclidean_ap": 0.564331,
        "dot_accuracy": 0.541392,
        "dot_accuracy_threshold": 0.870653,
        "dot_f1": 0.666667,
        "dot_f1_threshold": -0.018127,
        "dot_precision": 0.5,
        "dot_recall": 1.0,
        "dot_ap": 0.564138,
        "max_accuracy": 0.541392,
        "max_f1": 0.667646,
        "max_precision": 0.504891,
        "max_recall": 1.0,
        "max_ap": 0.564331,
        "main_score": 0.564331,
        "hf_subset": "th",
        "languages": [
          "tha-Thai"
        ]
      },
      {
        "similarity_accuracy": 0.586813,
        "similarity_accuracy_threshold": 0.546629,
        "similarity_f1": 0.670659,
        "similarity_f1_threshold": 0.198821,
        "similarity_precision": 0.508321,
        "similarity_recall": 0.985337,
        "similarity_ap": 0.615484,
        "cosine_accuracy": 0.586813,
        "cosine_accuracy_threshold": 0.546629,
        "cosine_f1": 0.670659,
        "cosine_f1_threshold": 0.198821,
        "cosine_precision": 0.508321,
        "cosine_recall": 0.985337,
        "cosine_ap": 0.615484,
        "manhattan_accuracy": 0.594139,
        "manhattan_accuracy_threshold": 10.286887,
        "manhattan_f1": 0.667994,
        "manhattan_f1_threshold": 13.394383,
        "manhattan_precision": 0.505652,
        "manhattan_recall": 0.983871,
        "manhattan_ap": 0.622278,
        "euclidean_accuracy": 0.586813,
        "euclidean_accuracy_threshold": 0.95223,
        "euclidean_f1": 0.670659,
        "euclidean_f1_threshold": 1.265841,
        "euclidean_precision": 0.508321,
        "euclidean_recall": 0.985337,
        "euclidean_ap": 0.615484,
        "dot_accuracy": 0.586813,
        "dot_accuracy_threshold": 0.546629,
        "dot_f1": 0.670659,
        "dot_f1_threshold": 0.198821,
        "dot_precision": 0.508321,
        "dot_recall": 0.985337,
        "dot_ap": 0.615484,
        "max_accuracy": 0.594139,
        "max_f1": 0.670659,
        "max_precision": 0.508321,
        "max_recall": 0.985337,
        "max_ap": 0.622278,
        "main_score": 0.622278,
        "hf_subset": "tr",
        "languages": [
          "tur-Latn"
        ]
      },
      {
        "similarity_accuracy": 0.576557,
        "similarity_accuracy_threshold": 0.760717,
        "similarity_f1": 0.666667,
        "similarity_f1_threshold": 0.0579,
        "similarity_precision": 0.5,
        "similarity_recall": 1.0,
        "similarity_ap": 0.598829,
        "cosine_accuracy": 0.576557,
        "cosine_accuracy_threshold": 0.760717,
        "cosine_f1": 0.666667,
        "cosine_f1_threshold": 0.0579,
        "cosine_precision": 0.5,
        "cosine_recall": 1.0,
        "cosine_ap": 0.598829,
        "manhattan_accuracy": 0.58315,
        "manhattan_accuracy_threshold": 7.858026,
        "manhattan_f1": 0.666993,
        "manhattan_f1_threshold": 13.590828,
        "manhattan_precision": 0.500367,
        "manhattan_recall": 1.0,
        "manhattan_ap": 0.604232,
        "euclidean_accuracy": 0.576557,
        "euclidean_accuracy_threshold": 0.691784,
        "euclidean_f1": 0.666667,
        "euclidean_f1_threshold": 1.372279,
        "euclidean_precision": 0.5,
        "euclidean_recall": 1.0,
        "euclidean_ap": 0.598829,
        "dot_accuracy": 0.576557,
        "dot_accuracy_threshold": 0.760717,
        "dot_f1": 0.666667,
        "dot_f1_threshold": 0.0579,
        "dot_precision": 0.5,
        "dot_recall": 1.0,
        "dot_ap": 0.598829,
        "max_accuracy": 0.58315,
        "max_f1": 0.666993,
        "max_precision": 0.500367,
        "max_recall": 1.0,
        "max_ap": 0.604232,
        "main_score": 0.604232,
        "hf_subset": "vi",
        "languages": [
          "vie-Latn"
        ]
      },
      {
        "similarity_accuracy": 0.581685,
        "similarity_accuracy_threshold": 0.898357,
        "similarity_f1": 0.667976,
        "similarity_f1_threshold": 0.595648,
        "similarity_precision": 0.502216,
        "similarity_recall": 0.997067,
        "similarity_ap": 0.606966,
        "cosine_accuracy": 0.581685,
        "cosine_accuracy_threshold": 0.898357,
        "cosine_f1": 0.667976,
        "cosine_f1_threshold": 0.595648,
        "cosine_precision": 0.502216,
        "cosine_recall": 0.997067,
        "cosine_ap": 0.606966,
        "manhattan_accuracy": 0.575824,
        "manhattan_accuracy_threshold": 5.22762,
        "manhattan_f1": 0.668352,
        "manhattan_f1_threshold": 8.624287,
        "manhattan_precision": 0.510031,
        "manhattan_recall": 0.969208,
        "manhattan_ap": 0.606456,
        "euclidean_accuracy": 0.581685,
        "euclidean_accuracy_threshold": 0.450872,
        "euclidean_f1": 0.667976,
        "euclidean_f1_threshold": 0.899186,
        "euclidean_precision": 0.502216,
        "euclidean_recall": 0.997067,
        "euclidean_ap": 0.606966,
        "dot_accuracy": 0.581685,
        "dot_accuracy_threshold": 0.898357,
        "dot_f1": 0.667976,
        "dot_f1_threshold": 0.595648,
        "dot_precision": 0.502216,
        "dot_recall": 0.997067,
        "dot_ap": 0.606966,
        "max_accuracy": 0.581685,
        "max_f1": 0.668352,
        "max_precision": 0.510031,
        "max_recall": 0.997067,
        "max_ap": 0.606966,
        "main_score": 0.606966,
        "hf_subset": "zh",
        "languages": [
          "zho-Hans"
        ]
      }
    ]
  },
  "evaluation_time": 2.617507219314575,
  "kg_co2_emissions": null
}